{
  "lastModifiedDate": "2023-06-08",
  "detail": {
    "slug": "moto-takagi-san",
    "series": {
      "kobo": "-W_sw2EinF-kUGgwpY7vCQ",
      "readmoo": 2193,
      "bw": 12758,
      "pubu": {
        "store": 29038,
        "id": "擅長捉弄人的(前)高木同學"
      }
    },
    "collection": {
      "books": [
        "E050065056",
        "E050065057",
        "E050065058",
        "E050082734",
        "E050092716",
        "E050095632",
        "E050131297"
      ]
    },
    "title": "擅長捉弄人的(前)高木同學",
    "originalTitle": "",
    "authors": [
      "山本崇一朗",
      "稻葉光史"
    ],
    "publisher": "尖端出版",
    "finished": false,
    "tags": [
      "戀愛",
      "夫婦"
    ]
  },
  "vols": [
    {
      "vol": 1,
      "volName": "(01)",
      "isbn": "9789571086453",
      "cover": "/moto-takagi-san/moto-takagi-san-1.webp",
      "pages": 146,
      "authors": [
        "山本崇一朗",
        "稻葉光史"
      ],
      "translators": [
        "泪紫音"
      ],
      "nsfw": false,
      "price": 98,
      "description": "★高木同學和西片結婚了!? 令人毫不意外的外傳登場！\n☆《擅長捉弄人的高木同學》動畫第2季2019年7月開播！\n★甜度爆表!!系列累計突破600萬冊！\n\n【故事簡介】\n孩子的媽很擅長捉弄人。\n\n超人氣愛情喜劇《擅長捉弄人的高木同學》裡的高木同學結婚了!!?\n媽媽與女兒，偶爾加上爸爸，\n前所未見的「捉弄系」家庭喜劇，強勢登場！\n\n本集收錄挑食、憋氣、泥團子、自行車與恐怖片等小故事，\n除了大家熟悉的西片與高木外，還有兩人調皮搗蛋的女兒‧小千！\n西片的個性加上高木同學的外表，小千今天也想盡辦法反將媽媽一軍！\n超大型後日談外傳，正式開跑！",
      "platform": {
        "kobo": {
          "id": "4BqvceczqTiEUFLKHfcrxQ",
          "date": "2020-03-10"
        },
        "bw": {
          "id": 84829,
          "date": "2020-03-10"
        },
        "readmoo": {
          "id": "210133419000101",
          "date": "2020-03-09",
          "version": "1.000"
        },
        "books": {
          "id": "E050065056",
          "date": "2019-07-30",
          "version": "V001.0001"
        },
        "pubu": {
          "id": 190502,
          "date": "2020-03-11",
          "type": [
            "pdf",
            "epub"
          ],
          "size": 100
        }
      },
      "epub": {
        "opf": {
          "modified": "2020-03-02",
          "width": 1111,
          "height": 1600
        },
        "img": {
          "modified": "",
          "width": 1414,
          "height": 2048
        }
      }
    },
    {
      "vol": 2,
      "volName": "(02)",
      "isbn": "9789571086460",
      "cover": "/moto-takagi-san/moto-takagi-san-2.webp",
      "pages": 146,
      "authors": [
        "山本崇一朗",
        "稻葉光史"
      ],
      "translators": [
        "泪紫音"
      ],
      "nsfw": false,
      "price": 98,
      "description": "★高木同學和西片結婚了!? 令人毫不意外的外傳登場！\n☆《擅長捉弄人的高木同學》動畫第2季2019年7月開播！\n★甜度爆表!!系列累計突破600萬冊！\n\n【故事簡介】\n孩子的媽很擅長捉弄人。\n\n超人氣愛情喜劇《擅長捉弄人的高木同學》裡的高木同學結婚了!!?\n媽媽與女兒，偶爾加上爸爸，\n前所未見的「捉弄系」家庭喜劇，強勢登場！\n\n本集收錄戳戳、迴圈、洗衣服、塗鴉與咖啡等小故事。\n不愧是兩人的女兒，小千也開始對捉弄人感興趣的樣子，\n西片當上爸爸後，不只要被(前)高木同學捉弄，連女兒都不放過他嗎？\n溫馨可愛之餘不忘甜蜜放閃的第二集！",
      "platform": {
        "kobo": {
          "id": "_JkCe_8VnjKK-37G16ka7Q",
          "date": "2020-03-10"
        },
        "bw": {
          "id": 84830,
          "date": "2020-03-10"
        },
        "readmoo": {
          "id": "210133420000101",
          "date": "2020-03-09",
          "version": "1.000"
        },
        "books": {
          "id": "E050065057",
          "date": "2019-07-30",
          "version": "V001.0001"
        },
        "pubu": {
          "id": 190505,
          "date": "2020-03-11",
          "type": [
            "pdf",
            "epub"
          ],
          "size": 94
        }
      },
      "epub": {
        "opf": {
          "modified": "2020-03-09",
          "width": 1418,
          "height": 2048
        },
        "img": {
          "modified": "",
          "width": 1418,
          "height": 2048
        }
      }
    },
    {
      "vol": 3,
      "volName": "(03)",
      "isbn": "9789571086477",
      "cover": "/moto-takagi-san/moto-takagi-san-3.webp",
      "pages": 146,
      "authors": [
        "山本崇一朗",
        "稻葉光史"
      ],
      "translators": [
        "泪紫音"
      ],
      "nsfw": false,
      "price": 98,
      "description": "★高木同學和西片結婚了!? 令人毫不意外的外傳登場！\n☆《擅長捉弄人的高木同學》動畫第2季2019年7月開播！\n★甜度爆表!!系列累計突破600萬冊！\n\n【故事簡介】\n孩子的媽很擅長捉弄人。\n\n超人氣愛情喜劇《擅長捉弄人的高木同學》裡的高木同學結婚了!!?\n媽媽與女兒，偶爾加上爸爸，\n前所未見的「捉弄系」家庭喜劇，強勢登場！\n\n本集收錄刷牙、晚餐、午睡、跳繩與扮家家酒等小故事。\n當上體育老師的西片與當上人妻的高木同學，\n加上遺傳到爸爸個性和媽媽外表的呆萌女兒‧小千，\n一家三口互相(?)捉弄的平凡日常。\n溫馨可愛之餘不忘甜蜜放閃的第三集！",
      "platform": {
        "kobo": {
          "id": "dXijscc3YTOnOcuFEKmEPw",
          "date": "2020-03-10"
        },
        "bw": {
          "id": 84831,
          "date": "2020-03-10"
        },
        "readmoo": {
          "id": "210133421000101",
          "date": "2020-03-09",
          "version": "1.000"
        },
        "books": {
          "id": "E050065058",
          "date": "2019-07-30",
          "version": "V001.0001"
        },
        "pubu": {
          "id": 190506,
          "date": "2020-03-11",
          "type": [
            "pdf",
            "epub"
          ],
          "size": 88
        }
      },
      "epub": {
        "opf": {
          "modified": "2020-03-09",
          "width": 1418,
          "height": 2048
        },
        "img": {
          "modified": "",
          "width": 1418,
          "height": 2048
        }
      }
    },
    {
      "vol": 4,
      "volName": "(04)",
      "isbn": "9789571092454",
      "cover": "/moto-takagi-san/moto-takagi-san-4.webp",
      "pages": 161,
      "authors": [
        "山本崇一朗",
        "稻葉光史"
      ],
      "translators": [
        "泪紫音"
      ],
      "nsfw": false,
      "price": 98,
      "description": "★高木同學和西片結婚了!? 令人毫不意外的外傳登場！\n☆《擅長捉弄人的高木同學》動畫第2季2019年7月開播！\n★甜度爆表!!系列累計突破600萬冊！\n\n【故事簡介】\n孩子的媽很擅長捉弄人。\n\n超人氣愛情喜劇《擅長捉弄人的高木同學》裡的高木同學結婚了!!?\n媽媽與女兒，偶爾加上爸爸，\n前所未見的「捉弄系」家庭喜劇，強勢登場！\n\n本集收錄劍玉、忍耐、雙載、晴天娃娃與肩膀按摩等小故事。\n當上體育老師的西片與當上人妻的(前)高木同學，\n加上遺傳到爸爸個性和媽媽外表的呆萌女兒‧小千，\n一家三口互相(?)捉弄的平凡日常。\n溫馨可愛之餘不忘甜蜜放閃的第四集！",
      "platform": {
        "kobo": {
          "id": "iyuRMgHqYTq7IhEcFQHLkw",
          "date": "2020-12-22"
        },
        "bw": {
          "id": 104842,
          "date": "2020-12-22"
        },
        "readmoo": {
          "id": "210165276000101",
          "date": "2020-12-22",
          "version": "1.000"
        },
        "books": {
          "id": "E050082734",
          "date": "2020-12-16",
          "version": "V001.0001"
        },
        "pubu": {
          "id": 215398,
          "date": "2020-12-24",
          "type": [
            "pdf",
            "epub"
          ],
          "size": 112
        }
      },
      "epub": {
        "opf": {
          "modified": "2020-12-21",
          "width": 1440,
          "height": 2048
        },
        "img": {
          "modified": "",
          "width": 1421,
          "height": 2048
        }
      }
    },
    {
      "vol": 5,
      "volName": "(05)",
      "isbn": "9789571097411",
      "cover": "/moto-takagi-san/moto-takagi-san-5.webp",
      "pages": 146,
      "authors": [
        "山本崇一朗",
        "稻葉光史"
      ],
      "translators": [
        "泪紫音"
      ],
      "nsfw": false,
      "price": 98,
      "description": "★高木同學和西片結婚了!? 令人毫不意外的外傳登場！\n☆《擅長捉弄人的高木同學》榮獲第66回小學館漫畫賞！\n★甜度爆表!!系列銷售累計突破600萬冊！\n\n【故事簡介】\n孩子的媽很擅長捉弄人。\n\n超人氣愛情喜劇《擅長捉弄人的高木同學》裡的高木同學結婚了!!?\n媽媽與女兒，偶爾加上爸爸，\n前所未見的「捉弄系」家庭喜劇，強勢登場！\n\n本集收錄尋寶、颱風、青椒、殭屍等等小故事。\n當上體育老師的西片與當上人妻的(前)高木同學，\n加上遺傳到爸爸個性和媽媽外表的呆萌女兒．小千，\n一家三口互相(?)捉弄的平凡日常。\n溫馨可愛之餘不忘甜蜜放閃的第五集！",
      "platform": {
        "kobo": {
          "id": "_8H6-eLwcz6gB4L9Gk6czw",
          "date": "2021-05-07"
        },
        "bw": {
          "id": 113095,
          "date": "2021-05-07"
        },
        "readmoo": {
          "id": "210179243000101",
          "date": "2021-05-06",
          "version": "1.000"
        },
        "books": {
          "id": "E050092716",
          "date": "2021-05-07",
          "version": "V001.0001"
        },
        "pubu": {
          "id": 232469,
          "date": "2021-09-27",
          "type": [
            "pdf",
            "epub"
          ],
          "size": 88
        }
      },
      "epub": {
        "opf": {
          "modified": "2021-05-05",
          "width": 1111,
          "height": 1600
        },
        "img": {
          "modified": "",
          "width": 1421,
          "height": 2048
        }
      }
    },
    {
      "vol": 6,
      "volName": "(06)",
      "isbn": "9786263027091",
      "cover": "/moto-takagi-san/moto-takagi-san-6.webp",
      "pages": 146,
      "authors": [
        "山本崇一朗",
        "稻葉光史"
      ],
      "translators": [
        "泪紫音"
      ],
      "nsfw": false,
      "price": 98,
      "description": "★高木同學和西片結婚了!? 令人毫不意外的外傳登場！\n☆《擅長捉弄人的高木同學》榮獲第66回小學館漫畫賞！\n★甜度爆表!!系列銷售累計突破600萬冊！\n\n【故事簡介】\n孩子的媽很擅長捉弄人。\n\n超人氣愛情喜劇《擅長捉弄人的高木同學》裡的高木同學結婚了!!?\n媽媽與女兒，偶爾加上爸爸，\n前所未見的「捉弄系」家庭喜劇，強勢登場！\n\n本集收錄鬼針草、聖誕老人、大掃除等等小故事。\n當上體育老師的西片與當上人妻的(前)高木同學，\n加上遺傳到爸爸個性和媽媽外表的呆萌女兒．小千，\n一家三口互相(?)捉弄的平凡日常。\n溫馨可愛之餘不忘甜蜜放閃的第六集！",
      "platform": {
        "kobo": {
          "id": "CVhFr-3BvzCwJtMTeOQsEA",
          "date": "2021-06-17"
        },
        "bw": {
          "id": 117748,
          "date": "2021-06-20"
        },
        "readmoo": {
          "id": "210183949000101",
          "date": "2021-06-16",
          "version": "1.000"
        },
        "books": {
          "id": "E050095632",
          "date": "2021-06-17",
          "version": "V001.0001"
        },
        "pubu": {
          "id": 237767,
          "date": "2021-09-27",
          "type": [
            "pdf",
            "epub"
          ],
          "size": 106
        }
      },
      "epub": {
        "opf": {
          "modified": "2021-06-17",
          "width": 1111,
          "height": 1600
        },
        "img": {
          "modified": "",
          "width": 1421,
          "height": 2048
        }
      }
    },
    {
      "vol": 7,
      "volName": "(07)",
      "isbn": "9786263165663",
      "cover": "/moto-takagi-san/moto-takagi-san-7.webp",
      "pages": 142,
      "authors": [
        "山本崇一朗",
        "稻葉光史"
      ],
      "translators": [
        "泪紫音"
      ],
      "nsfw": false,
      "price": 98,
      "description": "★高木同學和西片結婚了!? 令人毫不意外的外傳登場！\n☆《擅長捉弄人的高木同學》榮獲第66回小學館漫畫賞！\n★甜度爆表!!系列銷售累計突破600萬冊！\n\n【故事簡介】\n孩子的媽很擅長捉弄人。\n\n超人氣愛情喜劇《擅長捉弄人的高木同學》裡的高木同學結婚了!!?\n媽媽與女兒，偶爾加上爸爸，\n前所未見的「捉弄系」家庭喜劇，強勢登場！\n\n本集收錄扮家家酒、工作、情書等等小故事。\n當上體育老師的西片與當上人妻的(前)高木同學，\n加上遺傳到爸爸個性和媽媽外表的呆萌女兒．小千，\n一家三口互相(?)捉弄的平凡日常。\n溫馨可愛之餘不忘甜蜜放閃的第七集！",
      "platform": {
        "kobo": {
          "id": "2ihQAA1mRTS2MsBshCGZlA",
          "date": "2022-05-04"
        },
        "bw": {
          "id": 139156,
          "date": "2022-05-05"
        },
        "readmoo": {
          "id": "210228014000101",
          "date": "2022-05-03",
          "version": "1.000"
        },
        "books": {
          "id": "E050131297",
          "date": "2022-03-16",
          "version": "V001.0001"
        },
        "pubu": {
          "id": 298766,
          "date": "2022-05-06",
          "type": [
            "pdf",
            "epub"
          ],
          "size": 125
        }
      },
      "epub": {
        "opf": {
          "modified": "2022-05-04",
          "width": 1408,
          "height": 2048
        },
        "img": {
          "modified": "",
          "width": 1405,
          "height": 2048
        }
      }
    }
  ]
}